odin_db/__init__.py
odin_db/models.py
odin_db-1.3.2.dist-info/METADATA
odin_db-1.3.2.dist-info/WHEEL
odin_db-1.3.2.dist-info/licenses/LICENSE
odin_db-1.3.2.dist-info/RECORD
