Metadata-Version: 2.4
Name: odin-db
Version: 1.3.2
Summary: Odin DB is a set of pydantic models to be able to interpret a .odin file.
Project-URL: Homepage, https://github.com/fvsolutions-common/odin-db.git
Author-email: Floris Verniewuer <floris@vernieuwe.eu>
License-Expression: MPL-2.0
License-File: LICENSE
Classifier: Intended Audience :: Developers
Classifier: License :: OSI Approved :: Mozilla Public License 2.0 (MPL 2.0)
Classifier: Programming Language :: Python :: 3
Classifier: Programming Language :: Python :: 3.10
Classifier: Programming Language :: Python :: 3.11
Classifier: Programming Language :: Python :: 3.12
Requires-Python: >=3.10
Requires-Dist: pydantic>=2.10.6
